yang_example/__init__.py
yang_example/yang_test.py
Yang_Lab-1.0.0.dist-info/LICENSE
Yang_Lab-1.0.0.dist-info/METADATA
Yang_Lab-1.0.0.dist-info/WHEEL
Yang_Lab-1.0.0.dist-info/top_level.txt
Yang_Lab-1.0.0.dist-info/RECORD
